[
  {
    "validator_pubkey": "5pPRHniefFjkiaArbGX3Y8NUysJmQ9tMZg3FrFGwHzSm",
    "bam_node_connection": "amsterdam-mainnet-bam-3-tee",
    "stake": 7779431.45,
    "stake_percentage": 1.8297
  },
  {
    "validator_pubkey": "GoeW4aFK4dGoekJySgUynWDxBZiQJqm8GDAF4H53tDK9",
    "bam_node_connection": "amsterdam-mainnet-bam-3-tee",
    "stake": 3468277.8,
    "stake_percentage": 0.8157
  },
  {
    "validator_pubkey": "krakeNd6ednDPEXxHAmoBs1qKVM8kLg79PvWF2mhXV1",
    "bam_node_connection": "dublin-mainnet-bam-1-tee",
    "stake": 2793756.85,
    "stake_percentage": 0.6571
  },
  {
    "validator_pubkey": "AWcCdYG7Dy6GX45c6QMPbgGwgRZPKcBDT4bXGb3QrVRV",
    "bam_node_connection": "frankfurt-mainnet-bam-1-tee",
    "stake": 2013801,
    "stake_percentage": 0.4736
  },
  {
    "validator_pubkey": "DrifTrN923QaouP89UxkQzFGbumKPCnfkNYQRwmZxatz",
    "bam_node_connection": "amsterdam-mainnet-bam-3-tee",
    "stake": 1991032.87,
    "stake_percentage": 0.4683
  },
  {
    "validator_pubkey": "6WgdYhhGE53WrZ7ywJA15hBVkw7CRbQ8yDBBTwmBtAHN",
    "bam_node_connection": "frankfurt-mainnet-bam-1-tee",
    "stake": 1927299.53,
    "stake_percentage": 0.4533
  },
  {
    "validator_pubkey": "CoG8d9Fp2TFJRkAmrPMiPsGhQWHzdTTVoegEp9svRgmJ",
    "bam_node_connection": "amsterdam-mainnet-bam-3-tee",
    "stake": 1922966.19,
    "stake_percentage": 0.4523
  },
  {
    "validator_pubkey": "CMPSSdrTnRQBiBGTyFpdCc3VMNuLWYWaSkE8Zh5z6gbd",
    "bam_node_connection": "frankfurt-mainnet-bam-1-tee",
    "stake": 1842610.63,
    "stake_percentage": 0.4334
  },
  {
    "validator_pubkey": "C1ocKDYMCm2ooWptMMnpd5VEB2Nx4UMJgRuYofysyzcA",
    "bam_node_connection": "ny-mainnet-bam-1-tee",
    "stake": 1622374.82,
    "stake_percentage": 0.3816
  },
  {
    "validator_pubkey": "7y5VhV4fkz6r4zUmH2UiwPjLwXzPL1PcV28or5NWkWRL",
    "bam_node_connection": "frankfurt-mainnet-bam-1-tee",
    "stake": 1566444.19,
    "stake_percentage": 0.3684
  },
  {
    "validator_pubkey": "GYx8kpp7SsRwtQEEsGQjAxb4hFMMmT91kFJuDeky3YGQ",
    "bam_node_connection": "tokyo-mainnet-bam-1-tee",
    "stake": 1478620.88,
    "stake_percentage": 0.3478
  },
  {
    "validator_pubkey": "FZ4MT1HYJHd9GK8D5mJ9f3r7irLaDL5NxBNLjGqrLqs9",
    "bam_node_connection": "amsterdam-mainnet-bam-3-tee",
    "stake": 1474579.96,
    "stake_percentage": 0.3468
  },
  {
    "validator_pubkey": "6TkKqq15wXjqEjNg9zqTKADwuVATR9dW3rkNnsYme1ea",
    "bam_node_connection": "amsterdam-mainnet-bam-3-tee",
    "stake": 1425188.82,
    "stake_percentage": 0.3352
  },
  {
    "validator_pubkey": "PUmpKiNnSVAZ3w4KaFX6jKSjXUNHFShGkXbERo54xjb",
    "bam_node_connection": "amsterdam-mainnet-bam-3-tee",
    "stake": 1172320.25,
    "stake_percentage": 0.2757
  },
  {
    "validator_pubkey": "AMukCLCr52XxsEjXoDxKKxjNg4FpnsReXNaQx8aR6DJF",
    "bam_node_connection": "amsterdam-mainnet-bam-3-tee",
    "stake": 965498.41,
    "stake_percentage": 0.2271
  },
  {
    "validator_pubkey": "4SsMncJdtKiUcDtukkX15mqei7WiuQ9yvRtQrQW4reWC",
    "bam_node_connection": "ny-mainnet-bam-1-tee",
    "stake": 899998.24,
    "stake_percentage": 0.2117
  },
  {
    "validator_pubkey": "AiDoLWFKzNxSXKeZ4zym2TEPkg6F4kQ3YBA8WhANVPEq",
    "bam_node_connection": "frankfurt-mainnet-bam-1-tee",
    "stake": 863980.76,
    "stake_percentage": 0.2032
  },
  {
    "validator_pubkey": "DB7DNWMVQASMFxcjkwdr4w4eg3NmfjWTk2rqFMMbrPLA",
    "bam_node_connection": "amsterdam-mainnet-bam-3-tee",
    "stake": 833186.46,
    "stake_percentage": 0.196
  },
  {
    "validator_pubkey": "AicQr2zCWBLiBwt2r6o7iTemmtyE7q5pTKyuuupbXEQA",
    "bam_node_connection": "pittsburgh-mainnet-bam-1-tee",
    "stake": 759796.58,
    "stake_percentage": 0.1787
  },
  {
    "validator_pubkey": "HzrEstnLfzsijhaD6z5frkSE2vWZEH5EUfn3bU9swo1f",
    "bam_node_connection": "amsterdam-mainnet-bam-3-tee",
    "stake": 729603.08,
    "stake_percentage": 0.1716
  },
  {
    "validator_pubkey": "Frog1Fks1AVN8ywFH3HTFeYojq6LQqoEPzgQFx2Kz5Ch",
    "bam_node_connection": "london-mainnet-bam-1-tee",
    "stake": 614662.33,
    "stake_percentage": 0.1446
  },
  {
    "validator_pubkey": "LA1NEzryoih6CQW3gwQqJQffK2mKgnXcjSQZSRpM3wc",
    "bam_node_connection": "london-mainnet-bam-1-tee",
    "stake": 611191.92,
    "stake_percentage": 0.1438
  },
  {
    "validator_pubkey": "7Zm1pE4FubFYZDyAQ5Labh3A4cxDcvve1s3WCRgEAZ84",
    "bam_node_connection": "amsterdam-mainnet-bam-3-tee",
    "stake": 607236.87,
    "stake_percentage": 0.1428
  },
  {
    "validator_pubkey": "7qGNnXKW1e3DsqEaSxwxMdBTFsrK73XtWTmkGitRyMQc",
    "bam_node_connection": "frankfurt-mainnet-bam-1-tee",
    "stake": 606429.19,
    "stake_percentage": 0.1426
  },
  {
    "validator_pubkey": "HH5dA42XF1HxNk1TRpG6LuKfLViMYNdAz5iWrFM4hWFi",
    "bam_node_connection": "amsterdam-mainnet-bam-3-tee",
    "stake": 593287.88,
    "stake_percentage": 0.1395
  },
  {
    "validator_pubkey": "GREEDkgav1ox1jYyd9Anv6exLqKV2vYnxMw5prGwmNKc",
    "bam_node_connection": "pittsburgh-mainnet-bam-1-tee",
    "stake": 545263.4,
    "stake_percentage": 0.1282
  },
  {
    "validator_pubkey": "ACvL73V4GNnxPVfZ7K89jCrYurLyzpEuE9qirjvh2Xmi",
    "bam_node_connection": "amsterdam-mainnet-bam-3-tee",
    "stake": 533715.63,
    "stake_percentage": 0.1255
  },
  {
    "validator_pubkey": "Va1idLRtYEtVFJFsvz8vtt1uCJgea4Q1zi2Rh3eraJh",
    "bam_node_connection": "amsterdam-mainnet-bam-3-tee",
    "stake": 530778.72,
    "stake_percentage": 0.1248
  },
  {
    "validator_pubkey": "bkpk9KVsDRfrArzzmkJ9mPEvbXfQxczzQYR3QMGiR8Z",
    "bam_node_connection": "slc-mainnet-bam-1-tee",
    "stake": 498051.76,
    "stake_percentage": 0.1171
  },
  {
    "validator_pubkey": "Cu9Ls6dsTL6cxFHZdStHwVSh1uy2ynXz8qPJMS5FRq86",
    "bam_node_connection": "frankfurt-mainnet-bam-1-tee",
    "stake": 461031.21,
    "stake_percentage": 0.1084
  },
  {
    "validator_pubkey": "vALigXFg9wnnhVHN16vNxHxXtAXiBv5QjAE6udoniBY",
    "bam_node_connection": "ny-mainnet-bam-1-tee",
    "stake": 451616.95,
    "stake_percentage": 0.1062
  },
  {
    "validator_pubkey": "TxtxXzLTDQ9W4ya3xgwyaqVa6Tky6Yqhi5BLpPCc9tZ",
    "bam_node_connection": "frankfurt-mainnet-bam-1-tee",
    "stake": 442201.64,
    "stake_percentage": 0.104
  },
  {
    "validator_pubkey": "mineL1YNwcRnxN93B2sX6q22R11WfRqxnY4NBV8KfFY",
    "bam_node_connection": "ny-mainnet-bam-1-tee",
    "stake": 428046.46,
    "stake_percentage": 0.1007
  },
  {
    "validator_pubkey": "6M53yM6dsE6hiaHgxWvYa4fsfzQTGyAZn7rM6JrzbqJV",
    "bam_node_connection": "frankfurt-mainnet-bam-1-tee",
    "stake": 413034.27,
    "stake_percentage": 0.0971
  },
  {
    "validator_pubkey": "A4hyMd3FyvUJSRafDUSwtLLaQcxRP4r1BRC9w2AJ1to2",
    "bam_node_connection": "singapore-mainnet-bam-1-tee",
    "stake": 364141.4,
    "stake_percentage": 0.0856
  },
  {
    "validator_pubkey": "CXPeim1wQMkcTvEHx9QdhgKREYYJD8bnaCCqPRwJ1to1",
    "bam_node_connection": "dublin-mainnet-bam-1-tee",
    "stake": 357584.59,
    "stake_percentage": 0.0841
  },
  {
    "validator_pubkey": "JC7bH7HSZoDhwggBXtRF31cVt71WiizY2J6YDDQfG5er",
    "bam_node_connection": "amsterdam-mainnet-bam-3-tee",
    "stake": 351746.23,
    "stake_percentage": 0.0827
  },
  {
    "validator_pubkey": "FyrwfMaomErzqrFUXMjCJ7mA4u81DsiDdrzC3MJD6d4j",
    "bam_node_connection": "singapore-mainnet-bam-1-tee",
    "stake": 328510.55,
    "stake_percentage": 0.0773
  },
  {
    "validator_pubkey": "4XspXDcJy3DWZsVdaXrt8pE1xhcLpXDKkhj9XyjmWWNy",
    "bam_node_connection": "frankfurt-mainnet-bam-1-tee",
    "stake": 327723.63,
    "stake_percentage": 0.0771
  },
  {
    "validator_pubkey": "ALPHA6rdHZkx1om79xp47vX1iZXcbM3qfEwLyttZ1T7R",
    "bam_node_connection": "frankfurt-mainnet-bam-1-tee",
    "stake": 302699.52,
    "stake_percentage": 0.0712
  },
  {
    "validator_pubkey": "7GkMBmtrTZz8QbjSe1sXvAUtz7Pp42SQxfT5ymmJD4We",
    "bam_node_connection": "ny-mainnet-bam-1-tee",
    "stake": 299219.29,
    "stake_percentage": 0.0704
  },
  {
    "validator_pubkey": "2oHUYyW2PU9VJh4XBs5TbGgzdernunvGqyKth3kxW4ns",
    "bam_node_connection": "amsterdam-mainnet-bam-3-tee",
    "stake": 298212.57,
    "stake_percentage": 0.0701
  },
  {
    "validator_pubkey": "5pZvwjSpGYCxpJeySwSbSAji7kZe4YntL7rQvXM3YcNT",
    "bam_node_connection": "frankfurt-mainnet-bam-1-tee",
    "stake": 293120.03,
    "stake_percentage": 0.0689
  },
  {
    "validator_pubkey": "9gFxqsXbFyrKXUkqpAatonn47uYZ7sEZSnMxhzQoXrUJ",
    "bam_node_connection": "amsterdam-mainnet-bam-3-tee",
    "stake": 284601.4,
    "stake_percentage": 0.0669
  },
  {
    "validator_pubkey": "GkFT5nmcFVmJiLwuE98PjdF3LReMeq4WbejFHfwrnsgw",
    "bam_node_connection": "amsterdam-mainnet-bam-3-tee",
    "stake": 279817.57,
    "stake_percentage": 0.0658
  },
  {
    "validator_pubkey": "PAWsME7oYbjt5TRNc11mBa33JhKnQr9AYherdr9YAZ6",
    "bam_node_connection": "amsterdam-mainnet-bam-3-tee",
    "stake": 273398.88,
    "stake_percentage": 0.0643
  },
  {
    "validator_pubkey": "5zm9g3zgAPWzX3wmUB2JtTkcwCqe74NWsTmt5wLFwCKK",
    "bam_node_connection": "frankfurt-mainnet-bam-1-tee",
    "stake": 266653.07,
    "stake_percentage": 0.0627
  },
  {
    "validator_pubkey": "61QB1Evn9E3noQtpJm4auFYyHSXS5FPgqKtPgwJJfEQk",
    "bam_node_connection": "london-mainnet-bam-1-tee",
    "stake": 266211.18,
    "stake_percentage": 0.0626
  },
  {
    "validator_pubkey": "3s97yjq2MhoPVPC3U9VeE3Z5S643Pweovg88ysvrQPw5",
    "bam_node_connection": "ny-mainnet-bam-1-tee",
    "stake": 265032.18,
    "stake_percentage": 0.0623
  },
  {
    "validator_pubkey": "spcti6GQVvinbtHU9UAkbXhjTcBJaba1NVx4tmK4M5F",
    "bam_node_connection": "amsterdam-mainnet-bam-3-tee",
    "stake": 263803.86,
    "stake_percentage": 0.062
  },
  {
    "validator_pubkey": "5essVpBYvocZkQnkrWsMDfRPwtp4BeihJRaweKLR4dRn",
    "bam_node_connection": "amsterdam-mainnet-bam-3-tee",
    "stake": 263232.17,
    "stake_percentage": 0.0619
  },
  {
    "validator_pubkey": "BeSovDCzhEAfgwDyXBuhmCFKsu5WQ3PaX61GEfteNzXM",
    "bam_node_connection": "pittsburgh-mainnet-bam-1-tee",
    "stake": 262347.15,
    "stake_percentage": 0.0617
  },
  {
    "validator_pubkey": "THWsLPufeq9LWs2H9vYPbtFwdxAHbQHvSbT6pztG8x1",
    "bam_node_connection": "amsterdam-mainnet-bam-3-tee",
    "stake": 257777.08,
    "stake_percentage": 0.0606
  },
  {
    "validator_pubkey": "3KiDz3wuZrJfsgKt5KEvRb1WPpbci1PWj78aPVF5ei3F",
    "bam_node_connection": "frankfurt-mainnet-bam-1-tee",
    "stake": 255934.28,
    "stake_percentage": 0.0602
  },
  {
    "validator_pubkey": "8ZQg3K1V1Z2BVJkjmnxpi43WKhjPGXphzu5QmBkJibSP",
    "bam_node_connection": "amsterdam-mainnet-bam-3-tee",
    "stake": 252167.34,
    "stake_percentage": 0.0593
  },
  {
    "validator_pubkey": "BNtHBLo1L2vAG7PBQ6mJvWz7GqVPxBnioXsY2Gjtubrg",
    "bam_node_connection": "frankfurt-mainnet-bam-1-tee",
    "stake": 246720.26,
    "stake_percentage": 0.058
  },
  {
    "validator_pubkey": "PAD9aPiKJGcbGxuVLbc8o4Vf65GPq3fJQ7PkHWuX6a8",
    "bam_node_connection": "frankfurt-mainnet-bam-1-tee",
    "stake": 246403.82,
    "stake_percentage": 0.058
  },
  {
    "validator_pubkey": "2mDrrmhSzpSyaF12izGk8hnFjtKCGeCFPwQHpRiJDby2",
    "bam_node_connection": "amsterdam-mainnet-bam-3-tee",
    "stake": 245088.05,
    "stake_percentage": 0.0576
  },
  {
    "validator_pubkey": "BR1aTt4ZZUCwWJDkSYf1hqkYJjo7Mb7Ar8iVTkeSwUB8",
    "bam_node_connection": "frankfurt-mainnet-bam-1-tee",
    "stake": 239376.44,
    "stake_percentage": 0.0563
  },
  {
    "validator_pubkey": "8Nvaxzif1NrdvxNkRetjT8xJvd33EHkKVrfL8EDkgaNy",
    "bam_node_connection": "frankfurt-mainnet-bam-1-tee",
    "stake": 237420.97,
    "stake_percentage": 0.0558
  },
  {
    "validator_pubkey": "3WDh9HgusCujDmXCVhophLrHvoKHQd1Sd4uFHz1Awo35",
    "bam_node_connection": "frankfurt-mainnet-bam-1-tee",
    "stake": 237174.08,
    "stake_percentage": 0.0558
  },
  {
    "validator_pubkey": "gridqZmeBcsUKT2Mv4M9YFHFN3tVLFb2TCtTcLD1cAd",
    "bam_node_connection": "singapore-mainnet-bam-1-tee",
    "stake": 237075.79,
    "stake_percentage": 0.0558
  },
  {
    "validator_pubkey": "DViARWAWKkxAzp4UCgbw5B9pLSrBY3PaztFErcwgVUKX",
    "bam_node_connection": "frankfurt-mainnet-bam-1-tee",
    "stake": 231548.26,
    "stake_percentage": 0.0545
  },
  {
    "validator_pubkey": "43Am3PKFeo9cACpqYL5Sk95rpVdxLw3Mc22PqRqZXEW2",
    "bam_node_connection": "amsterdam-mainnet-bam-3-tee",
    "stake": 228303.5,
    "stake_percentage": 0.0537
  },
  {
    "validator_pubkey": "57i31UEyDg4koaZMZ1wAHbYuezXv3AVaHtvJgJarxt3f",
    "bam_node_connection": "amsterdam-mainnet-bam-3-tee",
    "stake": 226860.58,
    "stake_percentage": 0.0534
  },
  {
    "validator_pubkey": "9bkyxgYxRrysC1ijd6iByp9idn112CnYTw243fdH2Uvr",
    "bam_node_connection": "ny-mainnet-bam-1-tee",
    "stake": 226432.61,
    "stake_percentage": 0.0533
  },
  {
    "validator_pubkey": "8n4pc4sCJtBeLfJdGyJn6EcZuhtfTiepRa9ExdJFdmEN",
    "bam_node_connection": "amsterdam-mainnet-bam-3-tee",
    "stake": 219356.83,
    "stake_percentage": 0.0516
  },
  {
    "validator_pubkey": "qZMH9GWnnBkx7aM1h98iKSv2Lz5N78nwNSocAxDQrbP",
    "bam_node_connection": "frankfurt-mainnet-bam-1-tee",
    "stake": 218858.57,
    "stake_percentage": 0.0515
  },
  {
    "validator_pubkey": "NordEHiwa6wT5TCjdeWJzpsA7DSmWQPqfSS7m2b6cv3",
    "bam_node_connection": "amsterdam-mainnet-bam-3-tee",
    "stake": 218187.18,
    "stake_percentage": 0.0513
  },
  {
    "validator_pubkey": "2gDeeRa3mwPPtw1CMWPkEhRWo9v5izNBBfEXanr8uibX",
    "bam_node_connection": "frankfurt-mainnet-bam-1-tee",
    "stake": 217116.33,
    "stake_percentage": 0.0511
  },
  {
    "validator_pubkey": "2XmhZKHmfjku3T3nC9xKhgr5bm1CAmWXqNsNt49mo82C",
    "bam_node_connection": "frankfurt-mainnet-bam-1-tee",
    "stake": 215943.25,
    "stake_percentage": 0.0508
  },
  {
    "validator_pubkey": "5zuNci3TV79w6zLoJZzbZujMvkVZb2FcSPhgv9aT24AK",
    "bam_node_connection": "singapore-mainnet-bam-1-tee",
    "stake": 215723.69,
    "stake_percentage": 0.0507
  },
  {
    "validator_pubkey": "Tri1F8B6YtjkBztGCwBNSLEZib1EAqMUEUM7dTT7ZG3",
    "bam_node_connection": "amsterdam-mainnet-bam-3-tee",
    "stake": 215125.57,
    "stake_percentage": 0.0506
  },
  {
    "validator_pubkey": "4VrjyXQT61WFSjuG3ehgqZUK1jqvYqB46veQbXLotq3n",
    "bam_node_connection": "london-mainnet-bam-1-tee",
    "stake": 214972.08,
    "stake_percentage": 0.0506
  },
  {
    "validator_pubkey": "3tzpLMWRkWucvTRWU5PjgKzN1iwJuV69yCCjmuuo4gTk",
    "bam_node_connection": "amsterdam-mainnet-bam-3-tee",
    "stake": 212206.92,
    "stake_percentage": 0.0499
  },
  {
    "validator_pubkey": "8GLRbAstsabZuZUx73AoyfGi1FRCWSUhRgMugFyofEz7",
    "bam_node_connection": "amsterdam-mainnet-bam-3-tee",
    "stake": 212145.13,
    "stake_percentage": 0.0499
  },
  {
    "validator_pubkey": "Av8EnYrPBnSJHK5e2wmTdnCpSy7nzmBgyFaUKSyLnBfe",
    "bam_node_connection": "ny-mainnet-bam-1-tee",
    "stake": 208552.98,
    "stake_percentage": 0.0491
  },
  {
    "validator_pubkey": "SLNDCSGTEsA6KHpgR32MBt9UAurZnVSJGUtW2tRpdU2",
    "bam_node_connection": "slc-mainnet-bam-1-tee",
    "stake": 208137.57,
    "stake_percentage": 0.049
  },
  {
    "validator_pubkey": "9FXD1NXrK6xFU8i4gLAgjj2iMEWTqJhSuQN8tQuDfm2e",
    "bam_node_connection": "frankfurt-mainnet-bam-1-tee",
    "stake": 205639.5,
    "stake_percentage": 0.0484
  },
  {
    "validator_pubkey": "8AkVj5aAtJ27tYXeq89cnSf68V43NarFHMx2iSDjZv7c",
    "bam_node_connection": "tokyo-mainnet-bam-1-tee",
    "stake": 203538.53,
    "stake_percentage": 0.0479
  },
  {
    "validator_pubkey": "KoLibrJsbABbtmtFPc7nPvDxT81rc4UPM7mY9xSLjpo",
    "bam_node_connection": "amsterdam-mainnet-bam-3-tee",
    "stake": 201280.94,
    "stake_percentage": 0.0473
  },
  {
    "validator_pubkey": "2t53LvZfskcpXkdwLaBnfZLbNgyVHPu2BNFpcRBaEBhM",
    "bam_node_connection": "frankfurt-mainnet-bam-1-tee",
    "stake": 200970.03,
    "stake_percentage": 0.0473
  },
  {
    "validator_pubkey": "91oPXTs2oq8VvJpQ5TnvXakFGnnJSpEB6HFWDtSctwMt",
    "bam_node_connection": "amsterdam-mainnet-bam-3-tee",
    "stake": 200751.12,
    "stake_percentage": 0.0472
  },
  {
    "validator_pubkey": "FwnWx7x99rGwLmipzz8ii15NqcHkKRo2oS1Y7j6LivgZ",
    "bam_node_connection": "amsterdam-mainnet-bam-3-tee",
    "stake": 199975.47,
    "stake_percentage": 0.047
  },
  {
    "validator_pubkey": "8pyp3vfVPRziYdAYEyqkwytdBbdVbQmHqfQAVDcRV3w",
    "bam_node_connection": "london-mainnet-bam-1-tee",
    "stake": 199745.1,
    "stake_percentage": 0.047
  },
  {
    "validator_pubkey": "vaoJKVZYPAsqc52T2nNQhABR1gU6Cy2koDKfCQaEiva",
    "bam_node_connection": "frankfurt-mainnet-bam-1-tee",
    "stake": 199668.39,
    "stake_percentage": 0.047
  },
  {
    "validator_pubkey": "5aD6KB8g4MPt3xJafmMmun86hHMDnoFiGbd5gYiMFZw7",
    "bam_node_connection": "singapore-mainnet-bam-1-tee",
    "stake": 198089.59,
    "stake_percentage": 0.0466
  },
  {
    "validator_pubkey": "UMi1r5J3SagSu4HC3waB3YFzbXi82rRSScgW2e8NTfr",
    "bam_node_connection": "london-mainnet-bam-1-tee",
    "stake": 197053.54,
    "stake_percentage": 0.0463
  },
  {
    "validator_pubkey": "GFXVa19rX6iwfs3sLS5UvX9Exu2usRsG4V5MRMDRo23V",
    "bam_node_connection": "frankfurt-mainnet-bam-1-tee",
    "stake": 196654.07,
    "stake_percentage": 0.0463
  },
  {
    "validator_pubkey": "CVRr5oHCAAooVbYze7CvXtRp4FUtkMCSqBZU7MVu8v8e",
    "bam_node_connection": "frankfurt-mainnet-bam-1-tee",
    "stake": 196071.19,
    "stake_percentage": 0.0461
  },
  {
    "validator_pubkey": "soLStaCk5TiGCpeLKa9Fvv6f5JQGMa6S3uhLh826e9N",
    "bam_node_connection": "frankfurt-mainnet-bam-1-tee",
    "stake": 195288.12,
    "stake_percentage": 0.0459
  },
  {
    "validator_pubkey": "1KXvrkPXwkGF6NK1zyzVuJqbXfpenPVPP6hoiK9bsK3",
    "bam_node_connection": "amsterdam-mainnet-bam-3-tee",
    "stake": 195126.86,
    "stake_percentage": 0.0459
  },
  {
    "validator_pubkey": "73hojLdq1vZDSxeVQEqVFJ4iwLngdvEJPEpEHkSdv6BZ",
    "bam_node_connection": "frankfurt-mainnet-bam-1-tee",
    "stake": 193783.19,
    "stake_percentage": 0.0456
  },
  {
    "validator_pubkey": "FjYEr2UCeFzNfAKiFrbhG34Zv8LxbmfHYAFhAfc7SLQL",
    "bam_node_connection": "amsterdam-mainnet-bam-3-tee",
    "stake": 193517.26,
    "stake_percentage": 0.0455
  },
  {
    "validator_pubkey": "5marvipGzf98hxnoJFXsZbGHSXcEQ3yRGJ4ps7D3V4ou",
    "bam_node_connection": "frankfurt-mainnet-bam-1-tee",
    "stake": 189759.98,
    "stake_percentage": 0.0446
  },
  {
    "validator_pubkey": "GwHH8ciFhR8vejWCqmg8FWZUCNtubPY2esALvy5tBvji",
    "bam_node_connection": "amsterdam-mainnet-bam-3-tee",
    "stake": 187629.83,
    "stake_percentage": 0.0441
  },
  {
    "validator_pubkey": "Crg1X8FftV44NmwfFvgREjanBQmyyS7NEu6duLU7Cyy6",
    "bam_node_connection": "amsterdam-mainnet-bam-3-tee",
    "stake": 187467.91,
    "stake_percentage": 0.0441
  },
  {
    "validator_pubkey": "DDnAqxJVFo2GVTujibHt5cjevHMSE9bo8HJaydHoshdp",
    "bam_node_connection": "amsterdam-mainnet-bam-3-tee",
    "stake": 186228.48,
    "stake_percentage": 0.0438
  },
  {
    "validator_pubkey": "mD1afZhSisoXfJLT8nYwSFANqjr1KPoDUEpYTEfFX1e",
    "bam_node_connection": "frankfurt-mainnet-bam-1-tee",
    "stake": 185242.46,
    "stake_percentage": 0.0436
  },
  {
    "validator_pubkey": "DiveRaPKviyDnQyiiMFdV4rujsCBJzMNvPjKfvGNLGvL",
    "bam_node_connection": "amsterdam-mainnet-bam-3-tee",
    "stake": 184913.94,
    "stake_percentage": 0.0435
  },
  {
    "validator_pubkey": "8ebFZA8NPLBZD91CwsG1HWQsa2B5Ludgdyf5Hi3sYhhs",
    "bam_node_connection": "amsterdam-mainnet-bam-3-tee",
    "stake": 183792.22,
    "stake_percentage": 0.0432
  },
  {
    "validator_pubkey": "MCFmmmXdzTKjBEoMggi8JGFJmd856uYSowuH2sCU5kx",
    "bam_node_connection": "frankfurt-mainnet-bam-1-tee",
    "stake": 183577.57,
    "stake_percentage": 0.0432
  },
  {
    "validator_pubkey": "popscoyTKVksa4TyTXw488b3vvFxM7qQEyTBeMQopKu",
    "bam_node_connection": "amsterdam-mainnet-bam-3-tee",
    "stake": 182195.08,
    "stake_percentage": 0.0429
  },
  {
    "validator_pubkey": "2uxEHizFmmnLekKG2LZJwxNabhpymEYfdVCpgDxjt87m",
    "bam_node_connection": "frankfurt-mainnet-bam-1-tee",
    "stake": 182059.51,
    "stake_percentage": 0.0428
  },
  {
    "validator_pubkey": "AsMpvJ3DZ2Ydu1WTRMAyMH4QjSLiUG39rKzfzvtE1bWr",
    "bam_node_connection": "amsterdam-mainnet-bam-3-tee",
    "stake": 181986.3,
    "stake_percentage": 0.0428
  },
  {
    "validator_pubkey": "ADjyeNzWd8yhEjCVyAqT87eqoyGRbimERQsNhFQcXjop",
    "bam_node_connection": "ny-mainnet-bam-1-tee",
    "stake": 181979.12,
    "stake_percentage": 0.0428
  },
  {
    "validator_pubkey": "4k6wgP5WPBKQpsFGtzuXNrjcTE2fKWLj17nDvFeG5zSF",
    "bam_node_connection": "amsterdam-mainnet-bam-3-tee",
    "stake": 181931.03,
    "stake_percentage": 0.0428
  },
  {
    "validator_pubkey": "Ee8dX3qtwrDRnxYK6NGQfmMeKT3Qpp2QZHpxiAiw23W9",
    "bam_node_connection": "ny-mainnet-bam-1-tee",
    "stake": 181353.35,
    "stake_percentage": 0.0427
  },
  {
    "validator_pubkey": "A23LfQn6khffj2hGhGfXr6P52W2pxrVcCaHVQLYQgiX2",
    "bam_node_connection": "amsterdam-mainnet-bam-3-tee",
    "stake": 181152.58,
    "stake_percentage": 0.0426
  },
  {
    "validator_pubkey": "4QNekaDqrLmUENqkVhGCJrgHziPxkX9kridbKwunx9su",
    "bam_node_connection": "amsterdam-mainnet-bam-3-tee",
    "stake": 176688.12,
    "stake_percentage": 0.0416
  },
  {
    "validator_pubkey": "N43JWBg42ZoUFMkHsRUVbP7wGVdxaHKanqaF9BBNiFC",
    "bam_node_connection": "frankfurt-mainnet-bam-1-tee",
    "stake": 176342.22,
    "stake_percentage": 0.0415
  },
  {
    "validator_pubkey": "3tm92VTxwyZ5MDhGoYR4tVTkwWYkzfam6hwBjauUACCk",
    "bam_node_connection": "singapore-mainnet-bam-1-tee",
    "stake": 175850.64,
    "stake_percentage": 0.0414
  },
  {
    "validator_pubkey": "ALp2GdA1eJV8vZHMHazCtTxNXe3BLUSco9LDASgjDs8R",
    "bam_node_connection": "amsterdam-mainnet-bam-3-tee",
    "stake": 174614.82,
    "stake_percentage": 0.0411
  },
  {
    "validator_pubkey": "4b1onMDEasBh4BuPekQWijx3BYR64hAE1z2jJyeZUkck",
    "bam_node_connection": "ny-mainnet-bam-1-tee",
    "stake": 173817.04,
    "stake_percentage": 0.0409
  },
  {
    "validator_pubkey": "nSGZ3tv2UhskkPqiB666yDVj7PTi9qKgDqvjHyw5JgM",
    "bam_node_connection": "lax-mainnet-bam-1-tee",
    "stake": 171990.26,
    "stake_percentage": 0.0405
  },
  {
    "validator_pubkey": "SscQkTYV2BFQYGGffAmTzvefrFrw6z9GNYiWHstVZ77",
    "bam_node_connection": "ny-mainnet-bam-1-tee",
    "stake": 171662.18,
    "stake_percentage": 0.0404
  },
  {
    "validator_pubkey": "ByszyWdqC3rVMWy8f6jwK5cmwkpwYdwsr7UL58xS5vnm",
    "bam_node_connection": "amsterdam-mainnet-bam-3-tee",
    "stake": 168729.22,
    "stake_percentage": 0.0397
  },
  {
    "validator_pubkey": "YuRBAsy9Stw1u46A8dMp7WQVBFweLP1PKuYibzYAMmQ",
    "bam_node_connection": "frankfurt-mainnet-bam-1-tee",
    "stake": 166169.54,
    "stake_percentage": 0.0391
  },
  {
    "validator_pubkey": "FSyAsxcE7g8pSSEu5nx7Hkz44rMZiYio5Wz8Lszh3Nbi",
    "bam_node_connection": "amsterdam-mainnet-bam-3-tee",
    "stake": 165210.52,
    "stake_percentage": 0.0389
  },
  {
    "validator_pubkey": "CTwsruptUccEtZGNxBDbuusHYxkBX3P6ndrxVjSG213y",
    "bam_node_connection": "singapore-mainnet-bam-1-tee",
    "stake": 164709.25,
    "stake_percentage": 0.0387
  },
  {
    "validator_pubkey": "4aRPyjsqqFsf5488a9QAaHJLQJMGwoL5P6wRtLmroe2d",
    "bam_node_connection": "frankfurt-mainnet-bam-1-tee",
    "stake": 164647.97,
    "stake_percentage": 0.0387
  },
  {
    "validator_pubkey": "BxkAkLR2W3agWtjMXBNvhxmB8vsn7zhjNQcyfost99KY",
    "bam_node_connection": "amsterdam-mainnet-bam-3-tee",
    "stake": 164447.4,
    "stake_percentage": 0.0387
  },
  {
    "validator_pubkey": "peNgUgnzs1jGogUPW8SThXMvzNpzKSNf3om78xVPAYx",
    "bam_node_connection": "amsterdam-mainnet-bam-3-tee",
    "stake": 163123.81,
    "stake_percentage": 0.0384
  },
  {
    "validator_pubkey": "BLUEHGDihXD9CqqC5XFSQzDC3aS5jASohb2BAsXaJokR",
    "bam_node_connection": "amsterdam-mainnet-bam-3-tee",
    "stake": 162112.52,
    "stake_percentage": 0.0381
  },
  {
    "validator_pubkey": "BPKAfGkkzF5u1QRjjB1nWYYbPMUCMPJe1xZPmwEMNMCT",
    "bam_node_connection": "frankfurt-mainnet-bam-1-tee",
    "stake": 162023.22,
    "stake_percentage": 0.0381
  },
  {
    "validator_pubkey": "2P9ZYA4vBoBBr56hrEFTmrd5ctuz3r7wtvRYmbgk6jRL",
    "bam_node_connection": "ny-mainnet-bam-1-tee",
    "stake": 160630.3,
    "stake_percentage": 0.0378
  },
  {
    "validator_pubkey": "bay3wXfJsu9ds1zQBoQQ4DUwFGs3NP6q4gca9WM5G1z",
    "bam_node_connection": "frankfurt-mainnet-bam-1-tee",
    "stake": 159323.02,
    "stake_percentage": 0.0375
  },
  {
    "validator_pubkey": "HVXXmNKkmDZbZwj74iL2Y9Wu4SyrchBoxAfFYVAktLrG",
    "bam_node_connection": "frankfurt-mainnet-bam-1-tee",
    "stake": 158792.21,
    "stake_percentage": 0.0373
  },
  {
    "validator_pubkey": "23U4mgK9DMCxsv2StC4y2qAptP25Xv5b2cybKCeJ1to3",
    "bam_node_connection": "frankfurt-mainnet-bam-1-tee",
    "stake": 158685.36,
    "stake_percentage": 0.0373
  },
  {
    "validator_pubkey": "By8MseMKtZQQaQjMHJiyetmc5AC8RZZv8C2ss33ktrHt",
    "bam_node_connection": "frankfurt-mainnet-bam-1-tee",
    "stake": 155901.08,
    "stake_percentage": 0.0367
  },
  {
    "validator_pubkey": "HW4zorvt6xDwhU36RqjcWNwU8YMj9tiqnAafBKW4cqV",
    "bam_node_connection": "amsterdam-mainnet-bam-3-tee",
    "stake": 155871.43,
    "stake_percentage": 0.0367
  },
  {
    "validator_pubkey": "6gnbmed7kzwQVQ7ghsjgEuCoYmGeWciV2qCwni6WS6HU",
    "bam_node_connection": "london-mainnet-bam-1-tee",
    "stake": 155708.37,
    "stake_percentage": 0.0366
  },
  {
    "validator_pubkey": "7nzTzRZzezmugqE5ZjHRMxarhXunpwZ2PUdjV7uYzt7A",
    "bam_node_connection": "frankfurt-mainnet-bam-1-tee",
    "stake": 155647.58,
    "stake_percentage": 0.0366
  },
  {
    "validator_pubkey": "8uPW9msN75rfaKiwy8y8NxEX5zSk2WejtVv5YhZr3jCo",
    "bam_node_connection": "frankfurt-mainnet-bam-1-tee",
    "stake": 154458.95,
    "stake_percentage": 0.0363
  },
  {
    "validator_pubkey": "DeXsDvvZzKhVux4YfDFE6p4acJLGzr8yKt5pSTjzZB8t",
    "bam_node_connection": "singapore-mainnet-bam-1-tee",
    "stake": 153674.04,
    "stake_percentage": 0.0361
  },
  {
    "validator_pubkey": "EydLxzdWfD434DDxZYXkTcajvK5VKH7p6CofEDCRUkJ4",
    "bam_node_connection": "london-mainnet-bam-1-tee",
    "stake": 153316.05,
    "stake_percentage": 0.0361
  },
  {
    "validator_pubkey": "6qwYjs5vCSEKaTMBbHinnW8fvdGj1r8cpzPoAV1EHKsw",
    "bam_node_connection": "london-mainnet-bam-1-tee",
    "stake": 152100.57,
    "stake_percentage": 0.0358
  },
  {
    "validator_pubkey": "5XKJwdKB2Hs7pkEXzifAysjSk6q7Rt6k5KfHwmAMPtoQ",
    "bam_node_connection": "amsterdam-mainnet-bam-3-tee",
    "stake": 150207.61,
    "stake_percentage": 0.0353
  },
  {
    "validator_pubkey": "vahMVcSS3v6uwyFormV7FDAUbQSHwmy6vUedp1P7L42",
    "bam_node_connection": "amsterdam-mainnet-bam-3-tee",
    "stake": 149716.43,
    "stake_percentage": 0.0352
  },
  {
    "validator_pubkey": "6xFDLX751L7H9d5fQT9sf2SM5RWWE9LDgqz25pPDbWoJ",
    "bam_node_connection": "amsterdam-mainnet-bam-3-tee",
    "stake": 148932.71,
    "stake_percentage": 0.035
  },
  {
    "validator_pubkey": "G4GT8z4AKWNoy3x6nuzxW83UfFXLXzrwn7DZQt4GvWdU",
    "bam_node_connection": "pittsburgh-mainnet-bam-1-tee",
    "stake": 144558.72,
    "stake_percentage": 0.034
  },
  {
    "validator_pubkey": "3V2xaccDpFib4DbTksdiveNDmiwpXBqSWyjSof3w1Bg7",
    "bam_node_connection": "frankfurt-mainnet-bam-1-tee",
    "stake": 142948.56,
    "stake_percentage": 0.0336
  },
  {
    "validator_pubkey": "Hj2jzpAp57KyM3SmnYwJbDVrQ8tTWizMon2hhzYzwxet",
    "bam_node_connection": "frankfurt-mainnet-bam-1-tee",
    "stake": 140894.74,
    "stake_percentage": 0.0331
  },
  {
    "validator_pubkey": "BirdeyeK5yooepHNNgaW2bGGDD2jmib4oSRFTHyELbZ1",
    "bam_node_connection": "amsterdam-mainnet-bam-3-tee",
    "stake": 139769.68,
    "stake_percentage": 0.0329
  },
  {
    "validator_pubkey": "6xUK9Nbonr4eoJNtHGoUEMmYKoPz5mipKzyDBv6deX4d",
    "bam_node_connection": "london-mainnet-bam-1-tee",
    "stake": 138582.47,
    "stake_percentage": 0.0326
  },
  {
    "validator_pubkey": "EUDis6LJeJzDHTEBgfHGQyjHp63XZkGkx4E69xunC2Ej",
    "bam_node_connection": "amsterdam-mainnet-bam-3-tee",
    "stake": 136938.12,
    "stake_percentage": 0.0322
  },
  {
    "validator_pubkey": "2zykwzzo1pd3H2oSj5j5SRLTvmpa9Nr2S2Bh8tTVd5Tq",
    "bam_node_connection": "london-mainnet-bam-1-tee",
    "stake": 135733.5,
    "stake_percentage": 0.0319
  },
  {
    "validator_pubkey": "HFTcVVrX93SJwYHAiiHAssb3c4zXqSsF4mNjg5arGPEj",
    "bam_node_connection": "amsterdam-mainnet-bam-3-tee",
    "stake": 133821.7,
    "stake_percentage": 0.0315
  },
  {
    "validator_pubkey": "4uH4G6YiD5G8rU3mtPg73C2Uqamrqedy3FboTZcZrh6x",
    "bam_node_connection": "frankfurt-mainnet-bam-1-tee",
    "stake": 133334.24,
    "stake_percentage": 0.0314
  },
  {
    "validator_pubkey": "7G4RfctwLLgqG4ZWfCirU8dfJd87mKQWgB4EHQRv8i7v",
    "bam_node_connection": "amsterdam-mainnet-bam-3-tee",
    "stake": 132925.74,
    "stake_percentage": 0.0313
  },
  {
    "validator_pubkey": "7Nu9ckgtjobZ3MkbadGFKEvRymYuah9HmcxiUJKMM9NB",
    "bam_node_connection": "frankfurt-mainnet-bam-1-tee",
    "stake": 132325.41,
    "stake_percentage": 0.0311
  },
  {
    "validator_pubkey": "CpuDNi3iVoHXbaT8gHpzKe6rqeBasoYjEKi21q7NRVJS",
    "bam_node_connection": "lax-mainnet-bam-1-tee",
    "stake": 132100.23,
    "stake_percentage": 0.0311
  },
  {
    "validator_pubkey": "DZKTNGR3r4Akj3G42ReZatKhkmgEXoZjk5Ed2tFwRyqm",
    "bam_node_connection": "amsterdam-mainnet-bam-3-tee",
    "stake": 131718.92,
    "stake_percentage": 0.031
  },
  {
    "validator_pubkey": "As9NxA9bCfhrVLAFyGeWG5X5iLYPGhU3R7nLfX3tN6am",
    "bam_node_connection": "amsterdam-mainnet-bam-3-tee",
    "stake": 131612.13,
    "stake_percentage": 0.031
  },
  {
    "validator_pubkey": "2UBhtRuyr9nvWsUnrbWrvJiYWEU8TVBD4PLYQJKiRa9H",
    "bam_node_connection": "frankfurt-mainnet-bam-1-tee",
    "stake": 129853.27,
    "stake_percentage": 0.0305
  },
  {
    "validator_pubkey": "EN5F2BU5juUEWr9zRNNqKuQMi9zBUY1YLPHV5EyMrvnW",
    "bam_node_connection": "london-mainnet-bam-1-tee",
    "stake": 129706.48,
    "stake_percentage": 0.0305
  },
  {
    "validator_pubkey": "RoYFUUD7QD9aQ34UCMcwfye8dC5YvJeXz2J3mmoy5S4",
    "bam_node_connection": "frankfurt-mainnet-bam-1-tee",
    "stake": 125836.81,
    "stake_percentage": 0.0296
  },
  {
    "validator_pubkey": "BSGMRbK97DcgLe4u4kfNQnmTVZGVnwdtKQBJqWRBTZxU",
    "bam_node_connection": "amsterdam-mainnet-bam-3-tee",
    "stake": 125615.07,
    "stake_percentage": 0.0295
  },
  {
    "validator_pubkey": "ETcW7iuVraMKLMJayNCCsr9bLvKrJPDczy1CMVMPmXTc",
    "bam_node_connection": "amsterdam-mainnet-bam-3-tee",
    "stake": 123064.14,
    "stake_percentage": 0.0289
  },
  {
    "validator_pubkey": "GK2YYwmQk58xA2k2SeugY3i334SJVViqTT8sT5wim3Dk",
    "bam_node_connection": "amsterdam-mainnet-bam-3-tee",
    "stake": 122600.6,
    "stake_percentage": 0.0288
  },
  {
    "validator_pubkey": "nebu15XQKGpxzhhckADBX9PgvGN5qk9RRJCFLKc118w",
    "bam_node_connection": "frankfurt-mainnet-bam-1-tee",
    "stake": 121930.73,
    "stake_percentage": 0.0287
  },
  {
    "validator_pubkey": "SWiz7QwnYPm61pWWUUkMhj4r5pZLP1SvYibdHcB2cov",
    "bam_node_connection": "frankfurt-mainnet-bam-1-tee",
    "stake": 121106.09,
    "stake_percentage": 0.0285
  },
  {
    "validator_pubkey": "FdH9QEQBxPQfaF2JpcjgdfcMnDb7rjZkCDRCWLRjTQwj",
    "bam_node_connection": "frankfurt-mainnet-bam-1-tee",
    "stake": 116898.66,
    "stake_percentage": 0.0275
  },
  {
    "validator_pubkey": "GGX3BEoZDqjxcw4AbCdu62ZTMrkpSgmPt81oP2mVuZNS",
    "bam_node_connection": "amsterdam-mainnet-bam-3-tee",
    "stake": 116265.41,
    "stake_percentage": 0.0273
  },
  {
    "validator_pubkey": "6Rk694kh1QTyQkirdb1uDZmS5xqG9bNaYtxx8d311Mr7",
    "bam_node_connection": "ny-mainnet-bam-1-tee",
    "stake": 115602.41,
    "stake_percentage": 0.0272
  },
  {
    "validator_pubkey": "BCS95L5JHBWHvWkcEJBEF3BH5QHxKcPeaTgoYmHLvfFh",
    "bam_node_connection": "frankfurt-mainnet-bam-1-tee",
    "stake": 112326.61,
    "stake_percentage": 0.0264
  },
  {
    "validator_pubkey": "HgozywotiKv4F5g3jCgideF3gh9sdD3vz4QtgXKjWCtB",
    "bam_node_connection": "amsterdam-mainnet-bam-3-tee",
    "stake": 112313.42,
    "stake_percentage": 0.0264
  },
  {
    "validator_pubkey": "GiYSnFRrXrmkJMC54A1j3K4xT6ZMfx1NSThEe5X2WpDe",
    "bam_node_connection": "ny-mainnet-bam-1-tee",
    "stake": 111072.18,
    "stake_percentage": 0.0261
  },
  {
    "validator_pubkey": "GqDCbnafLmKkdqiqf278jDLXqjjZMB2sViZQtR82jPUf",
    "bam_node_connection": "slc-mainnet-bam-1-tee",
    "stake": 109506.32,
    "stake_percentage": 0.0258
  },
  {
    "validator_pubkey": "parafiUS6h6oLhCFwhjvEmQJKw8pF1iXsxMJdTq46dS",
    "bam_node_connection": "slc-mainnet-bam-1-tee",
    "stake": 108958.79,
    "stake_percentage": 0.0256
  },
  {
    "validator_pubkey": "PoN1E3VyqwqoGQEhC8ExpkRKTuyhxtGLnHHH3DwbgTU",
    "bam_node_connection": "london-mainnet-bam-1-tee",
    "stake": 108750.9,
    "stake_percentage": 0.0256
  },
  {
    "validator_pubkey": "9q16BB7WGmBxf1nJTdxH5zPnBUhtHqdqXqRFjSjuM4k7",
    "bam_node_connection": "amsterdam-mainnet-bam-3-tee",
    "stake": 106460.36,
    "stake_percentage": 0.025
  },
  {
    "validator_pubkey": "THE1CosYJD9F1eBq53Fg4MZYZa5WrPUf2RQU5ZHnfEj",
    "bam_node_connection": "amsterdam-mainnet-bam-3-tee",
    "stake": 104501.83,
    "stake_percentage": 0.0246
  },
  {
    "validator_pubkey": "2Eq6YD8P8QXTeoz9h6JHjgZ55t8RSxNdx4waMDCoPmQU",
    "bam_node_connection": "lax-mainnet-bam-1-tee",
    "stake": 103781.64,
    "stake_percentage": 0.0244
  },
  {
    "validator_pubkey": "3DaPk6TdeGnEBwTR8fEyZSLkdayk6vZXrqGZhAgYK8BV",
    "bam_node_connection": "tokyo-mainnet-bam-1-tee",
    "stake": 102381.85,
    "stake_percentage": 0.0241
  },
  {
    "validator_pubkey": "DnQBmTJyLbBMgJYQLJDqJz25AJModNkyexL5LdVRGnG4",
    "bam_node_connection": "amsterdam-mainnet-bam-3-tee",
    "stake": 100927.65,
    "stake_percentage": 0.0237
  },
  {
    "validator_pubkey": "CpgSfd6QUoBw1267rTtJoZhELqC5q7isKLojBifSbNEE",
    "bam_node_connection": "amsterdam-mainnet-bam-3-tee",
    "stake": 100599.78,
    "stake_percentage": 0.0237
  },
  {
    "validator_pubkey": "RoYLttggWwa2st3KAGEjnPhsq4NPD5QwaNVyyR8pTz4",
    "bam_node_connection": "frankfurt-mainnet-bam-1-tee",
    "stake": 98582.08,
    "stake_percentage": 0.0232
  },
  {
    "validator_pubkey": "hnhCMmnrmod4rcyc3QRKkLEC9XnPTvYJ2gBvjgFiV4o",
    "bam_node_connection": "london-mainnet-bam-1-tee",
    "stake": 98563.85,
    "stake_percentage": 0.0232
  },
  {
    "validator_pubkey": "dst2u7mXMyDvb14cSErRNA1mxH1d5VXbSXgZ3DKE9xH",
    "bam_node_connection": "london-mainnet-bam-1-tee",
    "stake": 97971.66,
    "stake_percentage": 0.023
  },
  {
    "validator_pubkey": "EWARp8Syq8cTWGWHtP5LT9fKAn5GvXfSCH8LfAwpgQ6m",
    "bam_node_connection": "ny-mainnet-bam-1-tee",
    "stake": 97699,
    "stake_percentage": 0.023
  },
  {
    "validator_pubkey": "CtvdyHYt8cMuGVHFarV2RADfoCdnrbd8e9jAsB225uMW",
    "bam_node_connection": "singapore-mainnet-bam-1-tee",
    "stake": 97607.42,
    "stake_percentage": 0.023
  },
  {
    "validator_pubkey": "1i1yPyh843bTfi5qPgqozTbDcEX65rUNEFcUT2KAs2i",
    "bam_node_connection": "frankfurt-mainnet-bam-1-tee",
    "stake": 97404.9,
    "stake_percentage": 0.0229
  },
  {
    "validator_pubkey": "3Rv6ZVGUuRczP76322LyhTTYw2iM4avV4B5xFJocQJer",
    "bam_node_connection": "ny-mainnet-bam-1-tee",
    "stake": 96963.95,
    "stake_percentage": 0.0228
  },
  {
    "validator_pubkey": "VicAQ3U2GjjAuF3tPCtEQZdZKnpAAxkr5Q3zjDKmdo7",
    "bam_node_connection": "london-mainnet-bam-1-tee",
    "stake": 96954.26,
    "stake_percentage": 0.0228
  },
  {
    "validator_pubkey": "9dH6wfdJVgnDcbCUjT8rkmejAzTnGQaFarmLfvBYXANK",
    "bam_node_connection": "london-mainnet-bam-1-tee",
    "stake": 96397.99,
    "stake_percentage": 0.0227
  },
  {
    "validator_pubkey": "7knvB4bbqHCKuNp3ef2hJWdwqoH6WAUi55NQt6LdRfkx",
    "bam_node_connection": "frankfurt-mainnet-bam-1-tee",
    "stake": 93973.7,
    "stake_percentage": 0.0221
  },
  {
    "validator_pubkey": "6pEtDovpyd1zUMYPuNhMCPU37sUTEAtzzgoVVAh1G1JL",
    "bam_node_connection": "amsterdam-mainnet-bam-3-tee",
    "stake": 93614.09,
    "stake_percentage": 0.022
  },
  {
    "validator_pubkey": "rssaJ2iKcE9QWsFYRZr8Q66TQh5bRk9DxYrzxGMzWQr",
    "bam_node_connection": "amsterdam-mainnet-bam-3-tee",
    "stake": 92934.85,
    "stake_percentage": 0.0219
  },
  {
    "validator_pubkey": "meshRrDTME9cL2FSQ9E56EncfkZ7vL8apwcCFsw3o6Y",
    "bam_node_connection": "singapore-mainnet-bam-1-tee",
    "stake": 92387.14,
    "stake_percentage": 0.0217
  },
  {
    "validator_pubkey": "D8xKNftHzFcCekENuTEcFC1eoL9y8wNHEg4Q5z57KK4e",
    "bam_node_connection": "tokyo-mainnet-bam-1-tee",
    "stake": 92140.57,
    "stake_percentage": 0.0217
  },
  {
    "validator_pubkey": "DP9iBgK9c7tJYb83KhxQMFNc1LXYu7nE7EhWpEzQnjmg",
    "bam_node_connection": "amsterdam-mainnet-bam-3-tee",
    "stake": 91783.61,
    "stake_percentage": 0.0216
  },
  {
    "validator_pubkey": "cybi55ebub37HZW9YmRaLh59Lh3kqaLTsEBQwW6vFkC",
    "bam_node_connection": "frankfurt-mainnet-bam-1-tee",
    "stake": 90508.27,
    "stake_percentage": 0.0213
  },
  {
    "validator_pubkey": "8aySXUFrqJz5kath6aVijrkBH8ZtxMWJGhYXwYBpKmHK",
    "bam_node_connection": "amsterdam-mainnet-bam-3-tee",
    "stake": 90279.06,
    "stake_percentage": 0.0212
  },
  {
    "validator_pubkey": "jntr1vkzvSujfckGR6ANmFmirVoPBMNr5XJGKP5uDQA",
    "bam_node_connection": "tokyo-mainnet-bam-1-tee",
    "stake": 89156.88,
    "stake_percentage": 0.021
  },
  {
    "validator_pubkey": "sTEVErNNwF2qPnV6DuNPkWpEyCt4UU6k2Y3Hyn7WUFu",
    "bam_node_connection": "london-mainnet-bam-1-tee",
    "stake": 88996.3,
    "stake_percentage": 0.0209
  },
  {
    "validator_pubkey": "DCKyEmMENQMtLXgbmUoHRmgP9XdJ9HsR5WxrKnSDCzKA",
    "bam_node_connection": "london-mainnet-bam-1-tee",
    "stake": 88989.76,
    "stake_percentage": 0.0209
  },
  {
    "validator_pubkey": "ECNnK4VjcKTsABiw8FAp3JCE6tCmYyrEJthYVyMazmxi",
    "bam_node_connection": "frankfurt-mainnet-bam-1-tee",
    "stake": 88920.52,
    "stake_percentage": 0.0209
  },
  {
    "validator_pubkey": "9ueKvL3WiLM4mNUZrfWqPTYY2Np5YwzFTYvAiPibx1Zq",
    "bam_node_connection": "frankfurt-mainnet-bam-1-tee",
    "stake": 88145.23,
    "stake_percentage": 0.0207
  },
  {
    "validator_pubkey": "AjGby82yXeYgj3kmng9y3c4nQpZFmiPpJKecLJTHbfbP",
    "bam_node_connection": "amsterdam-mainnet-bam-3-tee",
    "stake": 88131.02,
    "stake_percentage": 0.0207
  },
  {
    "validator_pubkey": "BJvrWSfonXnS2Km8iA9KLY6D6vS3GcsaUwUNPFBumTca",
    "bam_node_connection": "amsterdam-mainnet-bam-3-tee",
    "stake": 87612.15,
    "stake_percentage": 0.0206
  },
  {
    "validator_pubkey": "chdvWr6T14nqGRFD37KY36dsvhkCtDaufW5rpu3AfHe",
    "bam_node_connection": "london-mainnet-bam-1-tee",
    "stake": 87145.39,
    "stake_percentage": 0.0205
  },
  {
    "validator_pubkey": "3CKKAoVi94EnfX8QcVxEmk8CAvZTc6nAYzXp1WkSUofX",
    "bam_node_connection": "slc-mainnet-bam-1-tee",
    "stake": 84820.71,
    "stake_percentage": 0.0199
  },
  {
    "validator_pubkey": "8augxYLUge2iWmitQMwbcBL5VQEpsM6aJdRofhwpnzyw",
    "bam_node_connection": "frankfurt-mainnet-bam-1-tee",
    "stake": 84212.3,
    "stake_percentage": 0.0198
  },
  {
    "validator_pubkey": "Fb77sbwgXmtjmkjkaoSckGp5yg3nqdtD8zf1dyxxiCSf",
    "bam_node_connection": "amsterdam-mainnet-bam-3-tee",
    "stake": 84205.41,
    "stake_percentage": 0.0198
  },
  {
    "validator_pubkey": "CBUGET5PnvLc3HvEeFYj64iTvdKhYV6pujTPDdDh785K",
    "bam_node_connection": "amsterdam-mainnet-bam-3-tee",
    "stake": 83152.16,
    "stake_percentage": 0.0196
  },
  {
    "validator_pubkey": "7PpXQgDb9eCHN1Uudgi77Wm89cRz4T85YgDw83qvaJXd",
    "bam_node_connection": "amsterdam-mainnet-bam-3-tee",
    "stake": 82374,
    "stake_percentage": 0.0194
  },
  {
    "validator_pubkey": "pitMDEaMmWmr7qP8HsNqarPQkd3jhZbLJibhhQnL5RG",
    "bam_node_connection": "amsterdam-mainnet-bam-3-tee",
    "stake": 81456.16,
    "stake_percentage": 0.0192
  },
  {
    "validator_pubkey": "DeepM3FDWaAb7o53rvyZk5YvHLG3FvDiVXJLRY78z51p",
    "bam_node_connection": "slc-mainnet-bam-1-tee",
    "stake": 78929.75,
    "stake_percentage": 0.0186
  },
  {
    "validator_pubkey": "MargusJeV9bkePFLWbbzRNsMVo3Re6h9wKB5Ago8Tfj",
    "bam_node_connection": "amsterdam-mainnet-bam-3-tee",
    "stake": 78164.85,
    "stake_percentage": 0.0184
  },
  {
    "validator_pubkey": "3BeharBd3j4sKQp7Qze27JLQLd9AEEwGTX9TC7dXYSNw",
    "bam_node_connection": "ny-mainnet-bam-1-tee",
    "stake": 77934.97,
    "stake_percentage": 0.0183
  },
  {
    "validator_pubkey": "5ysfTZ42VT1TjnjzQShZSrix7wdVtjXwssocSeYKDs5d",
    "bam_node_connection": "frankfurt-mainnet-bam-1-tee",
    "stake": 77054.03,
    "stake_percentage": 0.0181
  },
  {
    "validator_pubkey": "KTMkUG8WCw9FdH44jLMBpc1teGafnYL6SgP4fHHbsNM",
    "bam_node_connection": "frankfurt-mainnet-bam-1-tee",
    "stake": 76751.83,
    "stake_percentage": 0.0181
  },
  {
    "validator_pubkey": "LTP1bMnfq1Z6UctyDXYHo9qcUJ6ReXm9cG2VwQcsHBt",
    "bam_node_connection": "frankfurt-mainnet-bam-1-tee",
    "stake": 76737.91,
    "stake_percentage": 0.018
  },
  {
    "validator_pubkey": "Fy7RCjDdFLG8wLn7TBKbccaKwYX1FetdSoVDREdUHf5o",
    "bam_node_connection": "london-mainnet-bam-1-tee",
    "stake": 74999.1,
    "stake_percentage": 0.0176
  },
  {
    "validator_pubkey": "4vdWYn2KbmQ3Dns5wVBfz4CFQDds4b7CpsC8MHBhHAib",
    "bam_node_connection": "frankfurt-mainnet-bam-1-tee",
    "stake": 74700.83,
    "stake_percentage": 0.0176
  },
  {
    "validator_pubkey": "7HMHSdQkjDwz9Q5zAhEy83uzW3XHJchjdpMYapKXcKt5",
    "bam_node_connection": "ny-mainnet-bam-1-tee",
    "stake": 74512.14,
    "stake_percentage": 0.0175
  },
  {
    "validator_pubkey": "DtY5Bzxd75iWQRvKwM2xLUxqwLT1RRoeNwmVvgS2JANA",
    "bam_node_connection": "london-mainnet-bam-1-tee",
    "stake": 74207.49,
    "stake_percentage": 0.0175
  },
  {
    "validator_pubkey": "2X7WoaXX9KPqNrNfvguhnwo3rjFPNsfw2t75fGjWRthz",
    "bam_node_connection": "frankfurt-mainnet-bam-1-tee",
    "stake": 71158.23,
    "stake_percentage": 0.0167
  },
  {
    "validator_pubkey": "8aPHvzVV91jZF948tykkoF6WfgLHppNfG8Z3V4gCrDix",
    "bam_node_connection": "amsterdam-mainnet-bam-3-tee",
    "stake": 71111.69,
    "stake_percentage": 0.0167
  },
  {
    "validator_pubkey": "TopjgY7N1fJdnW89S9fX6t7LF61nspgXGL1NpgAKhDG",
    "bam_node_connection": "frankfurt-mainnet-bam-1-tee",
    "stake": 71049.48,
    "stake_percentage": 0.0167
  },
  {
    "validator_pubkey": "SPHERExTW7GaMgS4RN6MbghYvXU2REfFWHgpxMH1P69",
    "bam_node_connection": "frankfurt-mainnet-bam-1-tee",
    "stake": 70628.26,
    "stake_percentage": 0.0166
  },
  {
    "validator_pubkey": "AdSHK6vpQnwHRSw7jXUwjMEytmhFwnynZSENhvpAxL1y",
    "bam_node_connection": "frankfurt-mainnet-bam-1-tee",
    "stake": 69666.85,
    "stake_percentage": 0.0164
  },
  {
    "validator_pubkey": "2E2JPuFhjkQvEJEeNGqVSwGLJa5GoFqabQTutGjg1bzw",
    "bam_node_connection": "slc-mainnet-bam-1-tee",
    "stake": 65632.84,
    "stake_percentage": 0.0154
  },
  {
    "validator_pubkey": "49j9bnkdgVNxLwsZ9h88sPR5MYEmsUyKrrJ6ZW8ijBrb",
    "bam_node_connection": "frankfurt-mainnet-bam-1-tee",
    "stake": 65256.15,
    "stake_percentage": 0.0153
  },
  {
    "validator_pubkey": "FNTPSUuRpDoJx1hwFmB5ncNLLMX42aE83P4hsFYUfNRL",
    "bam_node_connection": "ny-mainnet-bam-1-tee",
    "stake": 64242.59,
    "stake_percentage": 0.0151
  },
  {
    "validator_pubkey": "4YGgmwyqztpJeAi3pzHQ4Gf9cWrMHCjZaWeWoCK6zz6X",
    "bam_node_connection": "frankfurt-mainnet-bam-1-tee",
    "stake": 63979.28,
    "stake_percentage": 0.015
  },
  {
    "validator_pubkey": "LunaowJnt875WWoqDkhHhE93SNYHa6tfFNVn1rqc57c",
    "bam_node_connection": "london-mainnet-bam-1-tee",
    "stake": 62858.4,
    "stake_percentage": 0.0148
  },
  {
    "validator_pubkey": "FFevTkywysWf8PJvH4DZkEp4v9ks9HJPJhZWbhhJiYnr",
    "bam_node_connection": "amsterdam-mainnet-bam-3-tee",
    "stake": 59389.17,
    "stake_percentage": 0.014
  },
  {
    "validator_pubkey": "9U4WqNGVywKt3gG9HSt9tGVXBDXJvgid6BVweRysaJmg",
    "bam_node_connection": "slc-mainnet-bam-1-tee",
    "stake": 59293.65,
    "stake_percentage": 0.0139
  },
  {
    "validator_pubkey": "2abwQG3v2xRemFxRszVHSfnjJNe9zu5X8duKgxjyLeaK",
    "bam_node_connection": "london-mainnet-bam-1-tee",
    "stake": 56901.78,
    "stake_percentage": 0.0134
  },
  {
    "validator_pubkey": "7pR7t5axFfkg2VZB1uAuFNUvpAeowq2v15J4gw5MmHTB",
    "bam_node_connection": "london-mainnet-bam-1-tee",
    "stake": 55384.98,
    "stake_percentage": 0.013
  },
  {
    "validator_pubkey": "65pHd5P2VrehonT1cdJ2JUnq5wi3WUgfL3A8RhYH7Kg7",
    "bam_node_connection": "amsterdam-mainnet-bam-3-tee",
    "stake": 52773.43,
    "stake_percentage": 0.0124
  },
  {
    "validator_pubkey": "5ZjxMYBbnKd4VFxLjAChSWMTeQ96147HnxZvQJxUseHV",
    "bam_node_connection": "amsterdam-mainnet-bam-3-tee",
    "stake": 50519.21,
    "stake_percentage": 0.0119
  },
  {
    "validator_pubkey": "NLMSHTjmSiRxGJPs3uaqtsFBC2dTGYwK41U18Nmw5kH",
    "bam_node_connection": "amsterdam-mainnet-bam-3-tee",
    "stake": 49791.88,
    "stake_percentage": 0.0117
  },
  {
    "validator_pubkey": "UNrgBLmc8JT6A3dxXY9DWeHvDezt2DZQbhg1KPQfqEL",
    "bam_node_connection": "london-mainnet-bam-1-tee",
    "stake": 47289.59,
    "stake_percentage": 0.0111
  },
  {
    "validator_pubkey": "6yVX5rkTR3NfgCuu37vkmLCeG2RLqKaJHLj4G6b4Dvzu",
    "bam_node_connection": "amsterdam-mainnet-bam-3-tee",
    "stake": 45161.93,
    "stake_percentage": 0.0106
  },
  {
    "validator_pubkey": "rapXHroUoGG3KvZ3qwjvGMdA7siWXwXpiNC1bYarvSC",
    "bam_node_connection": "frankfurt-mainnet-bam-1-tee",
    "stake": 43987.52,
    "stake_percentage": 0.0103
  },
  {
    "validator_pubkey": "LiFiDJwJjW98MB8wxcnXpafKYsuz1hwpUkuszkERiX6",
    "bam_node_connection": "frankfurt-mainnet-bam-1-tee",
    "stake": 43135.7,
    "stake_percentage": 0.0101
  },
  {
    "validator_pubkey": "SENDa18d6LsC1f85AJXXMncBxQyFQKSJWZ1jaop5K87",
    "bam_node_connection": "amsterdam-mainnet-bam-3-tee",
    "stake": 40644.94,
    "stake_percentage": 0.0096
  },
  {
    "validator_pubkey": "parayLyZvwnGjDT2pGqrVn8UDxmNcdNQCE8uPRWMeRz",
    "bam_node_connection": "frankfurt-mainnet-bam-1-tee",
    "stake": 38362.55,
    "stake_percentage": 0.009
  },
  {
    "validator_pubkey": "4GEEKSwuiBHWTff9WaqrDcToZjbX6KYdyB4c578Zxse2",
    "bam_node_connection": "ny-mainnet-bam-1-tee",
    "stake": 37741.36,
    "stake_percentage": 0.0089
  },
  {
    "validator_pubkey": "FphFJA451qptiGyCeCN3xvrDi8cApGAnyR5vw2KxxQ1q",
    "bam_node_connection": "amsterdam-mainnet-bam-3-tee",
    "stake": 36543.98,
    "stake_percentage": 0.0086
  },
  {
    "validator_pubkey": "1Link6hB1NpkCwJt3ZtpQKZszKauhEcKgiWjaU8PRDG",
    "bam_node_connection": "frankfurt-mainnet-bam-1-tee",
    "stake": 36234.41,
    "stake_percentage": 0.0085
  },
  {
    "validator_pubkey": "MargusHP4dQyxrBuCWngzJp6EZSvg1aPNxdgpXykfr4",
    "bam_node_connection": "amsterdam-mainnet-bam-3-tee",
    "stake": 36100.08,
    "stake_percentage": 0.0085
  },
  {
    "validator_pubkey": "ACTGYsH7bHbaSP7z9N86oLPHBThAELbGfTboc1VoFeZz",
    "bam_node_connection": "frankfurt-mainnet-bam-1-tee",
    "stake": 35210.28,
    "stake_percentage": 0.0083
  },
  {
    "validator_pubkey": "5HCTsoKM7vwjubSZSyVWChaHQ9sNNRB1d2SuvL3eZ6Y6",
    "bam_node_connection": "frankfurt-mainnet-bam-1-tee",
    "stake": 34331.12,
    "stake_percentage": 0.0081
  },
  {
    "validator_pubkey": "6YDWxPaJWpZxJ6JLGaBeTJaGQn3gi3Pwtivii9cDyDHo",
    "bam_node_connection": "amsterdam-mainnet-bam-3-tee",
    "stake": 33282.64,
    "stake_percentage": 0.0078
  },
  {
    "validator_pubkey": "HrWYa5vKZrcDbQWE39SGYwyzYcbsmXfBiHJGxpasymm",
    "bam_node_connection": "frankfurt-mainnet-bam-1-tee",
    "stake": 33169.29,
    "stake_percentage": 0.0078
  },
  {
    "validator_pubkey": "UZBmptMjMSQEPKm4WyUkJeAuvZSqTuNK3cQCKFqJcXT",
    "bam_node_connection": "frankfurt-mainnet-bam-1-tee",
    "stake": 32984.66,
    "stake_percentage": 0.0078
  },
  {
    "validator_pubkey": "AWZhUiQjrjtxL8MEMWsCFbMausFQKkdTnDsFW2i411hN",
    "bam_node_connection": "frankfurt-mainnet-bam-1-tee",
    "stake": 29733.87,
    "stake_percentage": 0.007
  },
  {
    "validator_pubkey": "LimeA3gMLb2SjxrKbP7NsWk1UwTZrw4B6Ctc9dmVU6E",
    "bam_node_connection": "frankfurt-mainnet-bam-1-tee",
    "stake": 29448.08,
    "stake_percentage": 0.0069
  },
  {
    "validator_pubkey": "fhsM2sxME8cHrrk3qvtMsRRDv5AoLFja7NjNnHeYZxe",
    "bam_node_connection": "frankfurt-mainnet-bam-1-tee",
    "stake": 29239.6,
    "stake_percentage": 0.0069
  },
  {
    "validator_pubkey": "EATpCzQNs8BzZh1mx1hXMAJm3o1MLXakTXr4UEmcsY7f",
    "bam_node_connection": "pittsburgh-mainnet-bam-1-tee",
    "stake": 28753.82,
    "stake_percentage": 0.0068
  },
  {
    "validator_pubkey": "7CR6whiYULVf1Knj4J5PxUS37opdk8UAx2WnDzBQKiVe",
    "bam_node_connection": "frankfurt-mainnet-bam-1-tee",
    "stake": 27011.03,
    "stake_percentage": 0.0064
  },
  {
    "validator_pubkey": "Lua1fxRRHCnjVAYdfGyv2GbUsRHGM2DN2wgpWuF2WSb",
    "bam_node_connection": "slc-mainnet-bam-1-tee",
    "stake": 22441.51,
    "stake_percentage": 0.0053
  },
  {
    "validator_pubkey": "2Ue9zGmDnvYRrJNEjuAdNkbbickw6fKWtbeNM7T2rakg",
    "bam_node_connection": "amsterdam-mainnet-bam-3-tee",
    "stake": 19872.18,
    "stake_percentage": 0.0047
  },
  {
    "validator_pubkey": "DupN8puwoPdFo9EYm8AXemEn9cMsore1QmZzfPaxyUG4",
    "bam_node_connection": "london-mainnet-bam-1-tee",
    "stake": 17427.14,
    "stake_percentage": 0.0041
  },
  {
    "validator_pubkey": "KAoSp3EudGqUBXv46tQoDwbZxSm3iXa9wM2aF4ySbJJ",
    "bam_node_connection": "amsterdam-mainnet-bam-3-tee",
    "stake": 16575.76,
    "stake_percentage": 0.0039
  },
  {
    "validator_pubkey": "KAW1LjxH73tRBd1XsaqsRsgeERFkg4WpdXUSqR4QjkW",
    "bam_node_connection": "amsterdam-mainnet-bam-3-tee",
    "stake": 16151.32,
    "stake_percentage": 0.0038
  },
  {
    "validator_pubkey": "CuStTdKU5nWev5YKxMHyFjiHYG2CnjZ3rrPa8r1G2hTw",
    "bam_node_connection": "amsterdam-mainnet-bam-3-tee",
    "stake": 15798.12,
    "stake_percentage": 0.0037
  },
  {
    "validator_pubkey": "chopskqnudaeCTENWzUjfFCBSLcxprqbdMoCAucAwfb",
    "bam_node_connection": "frankfurt-mainnet-bam-1-tee",
    "stake": 14250.36,
    "stake_percentage": 0.0034
  }
]